{"algorithm_链表_移除链表元素.md":"2dc85dba","algorithm_bfs-dfs.md":"5eedaffa","network-protocol_02.tcp报文.md":"dd9474cb","algorithm_sort_heapsort.md":"c62e6c59","algorithm_math.md":"ddf74cf9","network-protocol_06.tcp和udp的区别.md":"a9c7e260","algorithm_二叉树_求二叉搜索树的属性.md":"f99d73a1","algorithm_sort_mergesort.md":"a86e0d4a","algorithm_sort_bubblesort.md":"94dd6e4d","algorithm_sort_quicksort.md":"4f068152","algorithm_sort_selectionsort.md":"fc16a21c","algorithm_二叉树_二叉树的遍历方式.md":"ecafa3a3","algorithm_动态规划_买卖股票的最佳时机.md":"bd220980","algorithm_动态规划_不同路径.md":"080df898","algorithm_链表_k个一组翻转链表.md":"c90541c4","algorithm_二叉树_二叉树的修改与构造2.md":"6bd80782","algorithm_动态规划_爬楼梯.md":"dffe6620","csrf.md":"39e30cfb","index.md":"bfdc2d75","algorithm_回溯_子集.md":"31b6fdb8","algorithm_回溯_字符串的排列.md":"e2d63969","algorithm_回溯_子集ii.md":"c812270d","algorithm_binarysearch.md":"5f05c7ac","algorithm_回溯_回溯排列.md":"2e29cfab","live-codes_iframe-postmessage_iframe-postmessage.md":"6753a726","live-codes_h5-drag_h5-drag.md":"3ef3e3d0","network-protocol_01.网络模型.md":"f375f4d8","algorithm_回溯_组合总和.md":"97398025","algorithm_回溯_总结.md":"3520f468","algorithm_字符串_千位分隔数.md":"edf4ad93","algorithm_贪心算法_贪心入门.md":"5f4c62f0","network-protocol_05.tcp中syn攻击.md":"e1b9f0f8","network-protocol_03.tcp三次握手.md":"d24181e0","network-protocol_04.tcp四次挥手.md":"3ade695c","algorithm_字符串_反转字符串ii.md":"2cc67e56","algorithm_字符串_回文系列.md":"b7b1292d","algorithm_深度遍历_单词搜索.md":"871fab67","network-protocol_09.http状态码.md":"75e88eec","network-protocol_dns.md":"79e717cb","algorithm_数组_合并两个有序数组.md":"783ff5a8","network-protocol_19.http2服务器推送功能.md":"ccc10c62","algorithm_字符串_字符串的排列.md":"f5f6ad86","network-protocol_10.http请求体和请求头.md":"45a0acd4","network-protocol_index.md":"307b1156","nginx gzip 不生效.md":"30a47da0","algorithm_字符串_最小覆盖子串.md":"22953057","algorithm_字符串_最长不含重复字符的子字符串.md":"b925436b","oauth2-github.md":"fc35b78a","network-protocol_11.cookie.md":"c50735be","network-protocol_13.http队头阻塞.md":"31b6af0b","network-protocol_16.https证书.md":"75432ab8","network-protocol_12.http优缺点.md":"a8c7a044","network-protocol_15.https的tsl连接过程.md":"b1375210","network-protocol_14.https改进了什么.md":"45f5b188","network-protocol_17.http2新功能.md":"003d25b7","network-protocol_18.http2剖析.md":"51ec3772","algorithm_数组_两数之和.md":"f8656efa","algorithm_数组_双指针.md":"aba0eb1d","algorithm_sort_countsort.md":"c28bd10a","algorithm_sort_insertsort.md":"6e185b33","algorithm_二叉树_二叉树的公共祖先.md":"c68ad266","certificate.md":"c8faee60","algorithm_链表_删除链表的倒数第n个结点.md":"2c3a715a","algorithm_二叉树_二叉树的修改与构造.md":"3110ba86","algorithm_动态规划_打家劫舍系列.md":"43b7640f","algorithm_动态规划_背包系列.md":"f29862c1","algorithm_链表_环形链表ii.md":"080bdc0e","algorithm_链表_相交链表.md":"91d56c52","algorithm_链表_反转链表.md":"6a93f418","algorithm_回溯_n皇后.md":"d5ddbbb4","algorithm_回溯_回溯分割.md":"ece15e77","algorithm_动态规划_连续.md":"36ff10e9","iframe 打开全屏无效.md":"5d4968a4","algorithm_动态规划_动态规划理论基础.md":"6f27bc21","eventloop.md":"06546f17","github-action.md":"76aa6bd7","algorithm_深度遍历_岛屿数量.md":"195af237","algorithm_深度遍历_螺旋矩阵.md":"e4f2ff6b","oauth2.md":"c0be9bf7","network-protocol_08.http的请求方法.md":"58ff147c","algorithm_数组_长度最小的子数组.md":"a5ae4cd6","network-protocol_07.http报文结构.md":"36bfcd2d","algorithm_二叉树_二叉树其他题目.md":"10ea4523","algorithm_sort_shellsort.md":"b121f8a6","network-protocol_cdn.md":"e1e09b79","network-protocol_20.http3.md":"fab73b50","浏览器缓存.md":"668ba8e3","algorithm_index.md":"029341cb","ssh.md":"22705062","algorithm_二叉树_二叉树的属性.md":"1a268be4"}
